<schemalist>
  <enum id="org.baedert.corebird.tweet-stack">
    <value nick="Never"    value="0"  />
    <value nick="Every"    value="1"  />
    <value nick="Stack 5"  value="5"  />
    <value nick="Stack 10" value="10" />
    <value nick="Stack 25" value="25" />
    <value nick="Stack 50" value="50" />
  </enum>

  <schema id="org.baedert.corebird"
      path="/org/baedert/corebird/"
      gettext-domain="corebird">

    <key name="use-dark-theme" type="b">
      <default>false</default>
      <summary>Specifies if Corebird should request to use the dark variant of the gtk theme</summary>
      <description></description>
    </key>

    <key name="new-tweets-notify" enum="org.baedert.corebird.tweet-stack">
      <default>"Never"</default>
      <summary>If/when the user should be notified about new tweets</summary>
      <description>
      </description>
    </key>
    <key name="new-mentions-notify" type="b">
      <default>true</default>
      <summary>Whether the user should be notified when another user mentions him in a tweet</summary>
      <description></description>
    </key>
    <key name="new-dms-notify" type="b">
      <default>true</default>
      <summary>Whether the user should be notified when another user writes him a direct message</summary>
      <description></description>
    </key>
    <key name="new-followers-notify" type="b">
      <default>true</default>
      <summary>Whether the user should be notified when another user starts following him</summary>
      <description></description>
    </key>
    <key name="show-inline-media" type="b">
      <default>true</default>
      <summary>Whether inline media should be downloaded/shown directly.</summary>
      <description>Disable this to save some bandwidth</description>
    </key>
    <key name="animation-duration" type="i">
      <default>300</default>
      <summary>Duration of slide animations[ms]</summary>
      <description></description>
    </key>
    <key name="startup-accounts" type="as">
      <default>[""]</default>
      <summary>List of accounts which will be opened when Corebird is started.</summary>
      <description></description>
    </key>
    <key name="auto-scroll-on-new-tweets" type="b">
      <default>false</default>
    </key>
    <key name="max-media-size" type="d">
      <default>2.0</default>
      <summary>Maximum size of inline media to download, in Megabytes.</summary>
    </key>
    <key name="sidebar-visible" type="b">
      <default>true</default>
      <summary>Whether to show the sidebar or not</summary>
    </key>
    <key name="accel-compose-tweet" type="s">
      <default>"&lt;Control&gt;T"</default>
        <summary>The accelerator to press in ordner to bring the ComposeTweetWindow up.
                 Muse be parseable with gtk_accelerator_parse
        </summary>
    </key>
     <key name="accel-toggle-sidebar" type="s">
       <default>"&lt;Control&gt;&lt;Shift&gt;S"</default>
       <summary>Accelerator to press in ordner to show/hide the sidebar</summary>
    </key>
    <key name="window-geometry" type="a{s(iiii)}">
      <default>{}</default>
      <summary></summary>
    </key>
    <key name="settings-geometry" type="(iiii)">
      <default>(0,0,500,300)</default>
      <summary>Size and position of the settings dialog</summary>
    </key>
  </schema>
</schemalist>
